pystackpath/__init__.py
pystackpath/config.py
pystackpath/util.py
pystackpath/stacks/__init__.py
pystackpath/stacks/certificates.py
pystackpath/stacks/metrics.py
pystackpath/stacks/cdnsites/__init__.py
pystackpath/stacks/cdnsites/scopes/__init__.py
pystackpath/stacks/cdnsites/scopes/configuration.py
pystackpath/stacks/cdnsites/scopes/origins.py
pystackpath/stacks/deliverysites/__init__.py
pystackpath/stacks/deliverysites/delivery_domain.py
pystackpath/stacks/wafsites/__init__.py
pystackpath/stacks/wafsites/api_login_urls.py
pystackpath/stacks/wafsites/api_urls.py
pystackpath/stacks/wafsites/ddos.py
pystackpath/stacks/wafsites/events.py
pystackpath/stacks/wafsites/monitoring.py
pystackpath/stacks/wafsites/requests.py
pystackpath/stacks/wafsites/rules.py
pystackpath/stacks/wafsites/traffic.py
pystackpath/stacks/wafsites/traffic_v2.py
pystackpath/stacks/wafsites/policy_groups/__init__.py
pystackpath/stacks/wafsites/policy_groups/policies.py
pystackpath/stacks/zones/__init__.py
pystackpath/stacks/zones/records.py
pystackpath-0.5.0.dist-info/LICENSE
pystackpath-0.5.0.dist-info/METADATA
pystackpath-0.5.0.dist-info/WHEEL
pystackpath-0.5.0.dist-info/top_level.txt
pystackpath-0.5.0.dist-info/RECORD
