Metadata-Version: 2.1
Name: pystackpath
Version: 0.5.0
Summary: A package to interact with StackPath
Home-page: https://github.com/NCCloud/pystackpath
Author: Sandro Modarelli
Author-email: sandro.modarelli@namecheap.com
License: UNKNOWN
Keywords: stackpath,cdn,waf,proxy,kubernetes
Platform: UNKNOWN
Classifier: Programming Language :: Python
Classifier: Programming Language :: Python :: 3.6
Classifier: License :: OSI Approved :: GNU General Public License v3 (GPLv3)
Classifier: Operating System :: OS Independent
Classifier: Intended Audience :: Developers
Classifier: Intended Audience :: Science/Research
Classifier: Topic :: Scientific/Engineering :: Artificial Intelligence
Classifier: Topic :: Internet :: WWW/HTTP :: Site Management
Classifier: Topic :: Software Development :: Libraries
